{
  "id": 18,
  "name": "pidgeot",
  "evolution_chain": {
    "url": "https://pokeapi.co/api/v2/evolution-chain/6/"
  },
  "flavor_text_entries": [
    {
      "flavor_text": "When hunting, it\nskims the surface\nof water at high\fspeed to pick off\nunwary prey such\nas MAGIKARP.",
      "language": {
        "name": "en",
        "url": "https://pokeapi.co/api/v2/language/9/"
      },
      "version": {
        "name": "red",
        "url": "https://pokeapi.co/api/v2/version/1/"
      }
    },
    {
      "flavor_text": "When hunting, it\nskims the surface\nof water at high\fspeed to pick off\nunwary prey such\nas MAGIKARP.",
      "language": {
        "name": "en",
        "url": "https://pokeapi.co/api/v2/language/9/"
      },
      "version": {
        "name": "blue",
        "url": "https://pokeapi.co/api/v2/version/2/"
      }
    },
    {
      "flavor_text": "This POKéMON flies\nat Mach 2 speed,\nseeking prey.\fIts large talons\nare feared as\nwicked weapons.",
      "language": {
        "name": "en",
        "url": "https://pokeapi.co/api/v2/language/9/"
      },
      "version": {
        "name": "yellow",
        "url": "https://pokeapi.co/api/v2/version/3/"
      }
    },
    {
      "flavor_text": "Its well-developed\nchest muscles make\nit strong enough\fto whip up a gusty\nwindstorm with\njust a few flaps.",
      "language": {
        "name": "en",
        "url": "https://pokeapi.co/api/v2/language/9/"
      },
      "version": {
        "name": "gold",
        "url": "https://pokeapi.co/api/v2/version/4/"
      }
    },
    {
      "flavor_text": "It spreads its\nbeautiful wings\nwide to frighten\fits enemies. It\ncan fly at Mach 2\nspeed.",
      "language": {
        "name": "en",
        "url": "https://pokeapi.co/api/v2/language/9/"
      },
      "version": {
        "name": "silver",
        "url": "https://pokeapi.co/api/v2/version/5/"
      }
    },
    {
      "flavor_text": "Its outstanding\nvision allows it\nto spot splashing\fMAGIKARP, even\nwhile flying at\n3300 feet.",
      "language": {
        "name": "en",
        "url": "https://pokeapi.co/api/v2/language/9/"
      },
      "version": {
        "name": "crystal",
        "url": "https://pokeapi.co/api/v2/version/6/"
      }
    },
    {
      "flavor_text": "This POKéMON has a dazzling plumage of\nbeautifully glossy feathers.\nMany TRAINERS are captivated by the\fstriking beauty of the feathers on its\nhead, compelling them to choose PIDGEOT\nas their POKéMON.",
      "language": {
        "name": "en",
        "url": "https://pokeapi.co/api/v2/language/9/"
      },
      "version": {
        "name": "ruby",
        "url": "https://pokeapi.co/api/v2/version/7/"
      }
    },
    {
      "flavor_text": "This POKéMON has a dazzling plumage of\nbeautifully glossy feathers.\nMany TRAINERS are captivated by the\fstriking beauty of the feathers on its\nhead, compelling them to choose PIDGEOT\nas their POKéMON.",
      "language": {
        "name": "en",
        "url": "https://pokeapi.co/api/v2/language/9/"
      },
      "version": {
        "name": "sapphire",
        "url": "https://pokeapi.co/api/v2/version/8/"
      }
    },
    {
      "flavor_text": "This POKéMON has gorgeous, glossy\nfeathers. Many TRAINERS are so captivated\nby the beautiful feathers on its head that\nthey choose PIDGEOT as their POKéMON.",
      "language": {
        "name": "en",
        "url": "https://pokeapi.co/api/v2/language/9/"
      },
      "version": {
        "name": "emerald",
        "url": "https://pokeapi.co/api/v2/version/9/"
      }
    },
    {
      "flavor_text": "It spreads its gorgeous wings widely to\nintimidate enemies. It races through the\nskies at Mach-2 speed.",
      "language": {
        "name": "en",
        "url": "https://pokeapi.co/api/v2/language/9/"
      },
      "version": {
        "name": "firered",
        "url": "https://pokeapi.co/api/v2/version/10/"
      }
    },
    {
      "flavor_text": "When hunting, it skims the surface of\nwater at high speed to pick off unwary\nprey such as MAGIKARP.",
      "language": {
        "name": "en",
        "url": "https://pokeapi.co/api/v2/language/9/"
      },
      "version": {
        "name": "leafgreen",
        "url": "https://pokeapi.co/api/v2/version/11/"
      }
    },
    {
      "flavor_text": "By flapping its wings with all its\nmight, PIDGEOT can make a gust of\nwind capable of bending tall trees.",
      "language": {
        "name": "en",
        "url": "https://pokeapi.co/api/v2/language/9/"
      },
      "version": {
        "name": "diamond",
        "url": "https://pokeapi.co/api/v2/version/12/"
      }
    },
    {
      "flavor_text": "By flapping its wings with all its\nmight, PIDGEOT can make a gust of\nwind capable of bending tall trees.",
      "language": {
        "name": "en",
        "url": "https://pokeapi.co/api/v2/language/9/"
      },
      "version": {
        "name": "pearl",
        "url": "https://pokeapi.co/api/v2/version/13/"
      }
    },
    {
      "flavor_text": "By flapping its wings with all its\nmight, PIDGEOT can make a gust of\nwind capable of bending tall trees.",
      "language": {
        "name": "en",
        "url": "https://pokeapi.co/api/v2/language/9/"
      },
      "version": {
        "name": "platinum",
        "url": "https://pokeapi.co/api/v2/version/14/"
      }
    },
    {
      "flavor_text": "Its well-developed chest muscles make\nit strong enough to whip up a gusty\nwindstorm with just a few flaps.",
      "language": {
        "name": "en",
        "url": "https://pokeapi.co/api/v2/language/9/"
      },
      "version": {
        "name": "heartgold",
        "url": "https://pokeapi.co/api/v2/version/15/"
      }
    },
    {
      "flavor_text": "It spreads its beautiful wings\nwide to frighten its enemies. It\ncan fly at Mach 2 speed.",
      "language": {
        "name": "en",
        "url": "https://pokeapi.co/api/v2/language/9/"
      },
      "version": {
        "name": "soulsilver",
        "url": "https://pokeapi.co/api/v2/version/16/"
      }
    },
    {
      "flavor_text": "By flapping its wings with all its\nmight, Pidgeot can make a gust of\nwind capable of bending tall trees.",
      "language": {
        "name": "en",
        "url": "https://pokeapi.co/api/v2/language/9/"
      },
      "version": {
        "name": "black",
        "url": "https://pokeapi.co/api/v2/version/17/"
      }
    },
    {
      "flavor_text": "By flapping its wings with all its\nmight, Pidgeot can make a gust of\nwind capable of bending tall trees.",
      "language": {
        "name": "en",
        "url": "https://pokeapi.co/api/v2/language/9/"
      },
      "version": {
        "name": "white",
        "url": "https://pokeapi.co/api/v2/version/18/"
      }
    },
    {
      "flavor_text": "By flapping its wings with all its\nmight, Pidgeot can make a gust of\nwind capable of bending tall trees.",
      "language": {
        "name": "en",
        "url": "https://pokeapi.co/api/v2/language/9/"
      },
      "version": {
        "name": "black-2",
        "url": "https://pokeapi.co/api/v2/version/21/"
      }
    },
    {
      "flavor_text": "By flapping its wings with all its\nmight, Pidgeot can make a gust of\nwind capable of bending tall trees.",
      "language": {
        "name": "en",
        "url": "https://pokeapi.co/api/v2/language/9/"
      },
      "version": {
        "name": "white-2",
        "url": "https://pokeapi.co/api/v2/version/22/"
      }
    },
    {
      "flavor_text": "When hunting, it skims the surface of water\nat high speed to pick off unwary prey such\nas Magikarp.",
      "language": {
        "name": "en",
        "url": "https://pokeapi.co/api/v2/language/9/"
      },
      "version": {
        "name": "x",
        "url": "https://pokeapi.co/api/v2/version/23/"
      }
    },
    {
      "flavor_text": "It spreads its gorgeous wings widely to intimidate\nenemies. It races through the skies at\nMach-2 speed.",
      "language": {
        "name": "en",
        "url": "https://pokeapi.co/api/v2/language/9/"
      },
      "version": {
        "name": "y",
        "url": "https://pokeapi.co/api/v2/version/24/"
      }
    },
    {
      "flavor_text": "This Pokémon has a dazzling plumage of beautifully\nglossy feathers. Many Trainers are captivated by the\nstriking beauty of the feathers on its head, compelling\nthem to choose Pidgeot as their Pokémon.",
      "language": {
        "name": "en",
        "url": "https://pokeapi.co/api/v2/language/9/"
      },
      "version": {
        "name": "omega-ruby",
        "url": "https://pokeapi.co/api/v2/version/25/"
      }
    },
    {
      "flavor_text": "This Pokémon has a dazzling plumage of beautifully\nglossy feathers. Many Trainers are captivated by the\nstriking beauty of the feathers on its head, compelling\nthem to choose Pidgeot as their Pokémon.",
      "language": {
        "name": "en",
        "url": "https://pokeapi.co/api/v2/language/9/"
      },
      "version": {
        "name": "alpha-sapphire",
        "url": "https://pokeapi.co/api/v2/version/26/"
      }
    },
    {
      "flavor_text": "This Pokémon flies at Mach 2 speed,\nseeking prey. Its large talons are feared\nas wicked weapons.",
      "language": {
        "name": "en",
        "url": "https://pokeapi.co/api/v2/language/9/"
      },
      "version": {
        "name": "lets-go-pikachu",
        "url": "https://pokeapi.co/api/v2/version/31/"
      }
    },
    {
      "flavor_text": "This Pokémon flies at Mach 2 speed,\nseeking prey. Its large talons are feared\nas wicked weapons.",
      "language": {
        "name": "en",
        "url": "https://pokeapi.co/api/v2/language/9/"
      },
      "version": {
        "name": "lets-go-eevee",
        "url": "https://pokeapi.co/api/v2/version/32/"
      }
    }
  ]
}