{
  "id": 39,
  "name": "jigglypuff",
  "evolution_chain": {
    "url": "https://pokeapi.co/api/v2/evolution-chain/16/"
  },
  "flavor_text_entries": [
    {
      "flavor_text": "When its huge eyes\nlight up, it sings\na mysteriously\fsoothing melody\nthat lulls its\nenemies to sleep.",
      "language": {
        "name": "en",
        "url": "https://pokeapi.co/api/v2/language/9/"
      },
      "version": {
        "name": "red",
        "url": "https://pokeapi.co/api/v2/version/1/"
      }
    },
    {
      "flavor_text": "When its huge eyes\nlight up, it sings\na mysteriously\fsoothing melody\nthat lulls its\nenemies to sleep.",
      "language": {
        "name": "en",
        "url": "https://pokeapi.co/api/v2/language/9/"
      },
      "version": {
        "name": "blue",
        "url": "https://pokeapi.co/api/v2/version/2/"
      }
    },
    {
      "flavor_text": "Uses its alluring\neyes to enrapture\nits foe. It then\fsings a pleasing\nmelody that lulls\nthe foe to sleep.",
      "language": {
        "name": "en",
        "url": "https://pokeapi.co/api/v2/language/9/"
      },
      "version": {
        "name": "yellow",
        "url": "https://pokeapi.co/api/v2/version/3/"
      }
    },
    {
      "flavor_text": "If it inflates to\nSING a lullaby, it\ncan perform longer\fand cause sure\ndrowsiness in its\naudience.",
      "language": {
        "name": "en",
        "url": "https://pokeapi.co/api/v2/language/9/"
      },
      "version": {
        "name": "gold",
        "url": "https://pokeapi.co/api/v2/version/4/"
      }
    },
    {
      "flavor_text": "Looking into its\ncute, round eyes\ncauses it to sing\fa relaxing melody,\ninducing its\nenemies to sleep.",
      "language": {
        "name": "en",
        "url": "https://pokeapi.co/api/v2/language/9/"
      },
      "version": {
        "name": "silver",
        "url": "https://pokeapi.co/api/v2/version/5/"
      }
    },
    {
      "flavor_text": "It rolls its cute\neyes as it sings a\nsoothing lullaby.\fIts gentle song\nputs anyone who\nhears it to sleep.",
      "language": {
        "name": "en",
        "url": "https://pokeapi.co/api/v2/language/9/"
      },
      "version": {
        "name": "crystal",
        "url": "https://pokeapi.co/api/v2/version/6/"
      }
    },
    {
      "flavor_text": "JIGGLYPUFF’s vocal chords can freely\nadjust the wavelength of its voice.\nThis POKéMON uses this ability to sing\fat precisely the right wavelength to\nmake its foes most drowsy.",
      "language": {
        "name": "en",
        "url": "https://pokeapi.co/api/v2/language/9/"
      },
      "version": {
        "name": "ruby",
        "url": "https://pokeapi.co/api/v2/version/7/"
      }
    },
    {
      "flavor_text": "When this POKéMON sings, it never\npauses to breathe. If it is in a battle\nagainst an opponent that does not\feasily fall asleep, JIGGLYPUFF cannot\nbreathe, endangering its life.",
      "language": {
        "name": "en",
        "url": "https://pokeapi.co/api/v2/language/9/"
      },
      "version": {
        "name": "sapphire",
        "url": "https://pokeapi.co/api/v2/version/8/"
      }
    },
    {
      "flavor_text": "Nothing can avoid falling asleep hearing a\nJIGGLYPUFF’s song. The sound waves of its\nsinging voice match the brain waves of\nsomeone in a deep sleep.",
      "language": {
        "name": "en",
        "url": "https://pokeapi.co/api/v2/language/9/"
      },
      "version": {
        "name": "emerald",
        "url": "https://pokeapi.co/api/v2/version/9/"
      }
    },
    {
      "flavor_text": "It captivates foes with its huge, round\neyes, then lulls them to sleep by singing\na soothing melody.",
      "language": {
        "name": "en",
        "url": "https://pokeapi.co/api/v2/language/9/"
      },
      "version": {
        "name": "firered",
        "url": "https://pokeapi.co/api/v2/version/10/"
      }
    },
    {
      "flavor_text": "When its huge eyes waver, it sings a\nmysteriously soothing melody that lulls\nits enemies to sleep.",
      "language": {
        "name": "en",
        "url": "https://pokeapi.co/api/v2/language/9/"
      },
      "version": {
        "name": "leafgreen",
        "url": "https://pokeapi.co/api/v2/version/11/"
      }
    },
    {
      "flavor_text": "When it wavers its big, round\neyes, it begins singing a lullaby\nthat makes everyone drowsy.",
      "language": {
        "name": "en",
        "url": "https://pokeapi.co/api/v2/language/9/"
      },
      "version": {
        "name": "diamond",
        "url": "https://pokeapi.co/api/v2/version/12/"
      }
    },
    {
      "flavor_text": "When it wavers its big, round\neyes, it begins singing a lullaby\nthat makes everyone drowsy.",
      "language": {
        "name": "en",
        "url": "https://pokeapi.co/api/v2/language/9/"
      },
      "version": {
        "name": "pearl",
        "url": "https://pokeapi.co/api/v2/version/13/"
      }
    },
    {
      "flavor_text": "When it wavers its big, round\neyes, it begins singing a lullaby\nthat makes everyone drowsy.",
      "language": {
        "name": "en",
        "url": "https://pokeapi.co/api/v2/language/9/"
      },
      "version": {
        "name": "platinum",
        "url": "https://pokeapi.co/api/v2/version/14/"
      }
    },
    {
      "flavor_text": "If it inflates to sing a lullaby,\nit can perform longer and cause\nsure drowsiness in its audience.",
      "language": {
        "name": "en",
        "url": "https://pokeapi.co/api/v2/language/9/"
      },
      "version": {
        "name": "heartgold",
        "url": "https://pokeapi.co/api/v2/version/15/"
      }
    },
    {
      "flavor_text": "Looking into its cute, round eyes\ncauses it to sing a relaxing melody,\ninducing its enemies to sleep.",
      "language": {
        "name": "en",
        "url": "https://pokeapi.co/api/v2/language/9/"
      },
      "version": {
        "name": "soulsilver",
        "url": "https://pokeapi.co/api/v2/version/16/"
      }
    },
    {
      "flavor_text": "When it wavers its big, round\neyes, it begins singing a lullaby\nthat makes everyone drowsy.",
      "language": {
        "name": "en",
        "url": "https://pokeapi.co/api/v2/language/9/"
      },
      "version": {
        "name": "black",
        "url": "https://pokeapi.co/api/v2/version/17/"
      }
    },
    {
      "flavor_text": "When it wavers its big, round\neyes, it begins singing a lullaby\nthat makes everyone drowsy.",
      "language": {
        "name": "en",
        "url": "https://pokeapi.co/api/v2/language/9/"
      },
      "version": {
        "name": "white",
        "url": "https://pokeapi.co/api/v2/version/18/"
      }
    },
    {
      "flavor_text": "Looking into its cute, round eyes makes\nit start singing a song so pleasant\nlisteners can’t help but fall asleep.",
      "language": {
        "name": "en",
        "url": "https://pokeapi.co/api/v2/language/9/"
      },
      "version": {
        "name": "black-2",
        "url": "https://pokeapi.co/api/v2/version/21/"
      }
    },
    {
      "flavor_text": "Looking into its cute, round eyes makes\nit start singing a song so pleasant\nlisteners can’t help but fall asleep.",
      "language": {
        "name": "en",
        "url": "https://pokeapi.co/api/v2/language/9/"
      },
      "version": {
        "name": "white-2",
        "url": "https://pokeapi.co/api/v2/version/22/"
      }
    },
    {
      "flavor_text": "It captivates foes with its huge, round eyes,\nthen lulls them to sleep by singing a\nsoothing melody.",
      "language": {
        "name": "en",
        "url": "https://pokeapi.co/api/v2/language/9/"
      },
      "version": {
        "name": "x",
        "url": "https://pokeapi.co/api/v2/version/23/"
      }
    },
    {
      "flavor_text": "If it inflates to sing a lullaby, it can perform longer\nand cause sure drowsiness in its audience.",
      "language": {
        "name": "en",
        "url": "https://pokeapi.co/api/v2/language/9/"
      },
      "version": {
        "name": "y",
        "url": "https://pokeapi.co/api/v2/version/24/"
      }
    },
    {
      "flavor_text": "Jigglypuff’s vocal cords can freely adjust the wavelength of its\nvoice. This Pokémon uses this ability to sing at precisely the\nright wavelength to make its foes most drowsy.",
      "language": {
        "name": "en",
        "url": "https://pokeapi.co/api/v2/language/9/"
      },
      "version": {
        "name": "omega-ruby",
        "url": "https://pokeapi.co/api/v2/version/25/"
      }
    },
    {
      "flavor_text": "When this Pokémon sings, it never pauses to breathe.\nIf it is in a battle against an opponent that does not easily\nfall asleep, Jigglypuff cannot breathe, endangering its life.",
      "language": {
        "name": "en",
        "url": "https://pokeapi.co/api/v2/language/9/"
      },
      "version": {
        "name": "alpha-sapphire",
        "url": "https://pokeapi.co/api/v2/version/26/"
      }
    },
    {
      "flavor_text": "It hugely inflates its stomach and sings a\nmysterious melody. If you hear this melody,\nyou’ll become sleepy right away.",
      "language": {
        "name": "en",
        "url": "https://pokeapi.co/api/v2/language/9/"
      },
      "version": {
        "name": "sun",
        "url": "https://pokeapi.co/api/v2/version/27/"
      }
    },
    {
      "flavor_text": "Jigglypuff possess a vocal range that exceeds\n12 octaves, but each individual’s singing skill\ndepends on its own effort.",
      "language": {
        "name": "en",
        "url": "https://pokeapi.co/api/v2/language/9/"
      },
      "version": {
        "name": "moon",
        "url": "https://pokeapi.co/api/v2/version/28/"
      }
    },
    {
      "flavor_text": "Recordings of Jigglypuff’s strange lullabies can\nbe purchased from department stores. These\nCDs can be found near the bedding area.",
      "language": {
        "name": "en",
        "url": "https://pokeapi.co/api/v2/language/9/"
      },
      "version": {
        "name": "ultra-sun",
        "url": "https://pokeapi.co/api/v2/version/29/"
      }
    },
    {
      "flavor_text": "The songs they sing are totally different\ndepending on the region they live in. Some even\nsound like they’re shouting!",
      "language": {
        "name": "en",
        "url": "https://pokeapi.co/api/v2/language/9/"
      },
      "version": {
        "name": "ultra-moon",
        "url": "https://pokeapi.co/api/v2/version/30/"
      }
    },
    {
      "flavor_text": "Uses its cute round eyes to enrapture its foe.\nIt then sings a pleasing melody that lulls\nthe foe to sleep.",
      "language": {
        "name": "en",
        "url": "https://pokeapi.co/api/v2/language/9/"
      },
      "version": {
        "name": "lets-go-pikachu",
        "url": "https://pokeapi.co/api/v2/version/31/"
      }
    },
    {
      "flavor_text": "Uses its cute round eyes to enrapture its foe.\nIt then sings a pleasing melody that lulls\nthe foe to sleep.",
      "language": {
        "name": "en",
        "url": "https://pokeapi.co/api/v2/language/9/"
      },
      "version": {
        "name": "lets-go-eevee",
        "url": "https://pokeapi.co/api/v2/version/32/"
      }
    },
    {
      "flavor_text": "Jigglypuff has top-notch lung capacity, even by\ncomparison to other Pokémon. It won’t stop\nsinging its lullabies until its foes fall asleep.",
      "language": {
        "name": "en",
        "url": "https://pokeapi.co/api/v2/language/9/"
      },
      "version": {
        "name": "sword",
        "url": "https://pokeapi.co/api/v2/version/33/"
      }
    },
    {
      "flavor_text": "By freely changing the wavelength of its voice,\nJigglypuff sings a mysterious melody sure to\nmake any listener sleepy.",
      "language": {
        "name": "en",
        "url": "https://pokeapi.co/api/v2/language/9/"
      },
      "version": {
        "name": "shield",
        "url": "https://pokeapi.co/api/v2/version/34/"
      }
    }
  ]
}