{
  "id": 436,
  "name": "bronzor",
  "evolution_chain": {
    "url": "https://pokeapi.co/api/v2/evolution-chain/224/"
  },
  "flavor_text_entries": [
    {
      "flavor_text": "Implements shaped like it were\ndiscovered in ancient tombs. It is\nunknown if they are related.",
      "language": {
        "name": "en",
        "url": "https://pokeapi.co/api/v2/language/9/"
      },
      "version": {
        "name": "diamond",
        "url": "https://pokeapi.co/api/v2/version/12/"
      }
    },
    {
      "flavor_text": "X-ray photos were taken to check\nits body structure. Nothing\nappeared, however.",
      "language": {
        "name": "en",
        "url": "https://pokeapi.co/api/v2/language/9/"
      },
      "version": {
        "name": "pearl",
        "url": "https://pokeapi.co/api/v2/version/13/"
      }
    },
    {
      "flavor_text": "There are researchers who believe\nthis Pokémon reflected like a mirror\nin the distant past.",
      "language": {
        "name": "en",
        "url": "https://pokeapi.co/api/v2/language/9/"
      },
      "version": {
        "name": "platinum",
        "url": "https://pokeapi.co/api/v2/version/14/"
      }
    },
    {
      "flavor_text": "Ancient people believed that the\npattern on BRONZOR’s back\ncontained a mysterious power.",
      "language": {
        "name": "en",
        "url": "https://pokeapi.co/api/v2/language/9/"
      },
      "version": {
        "name": "heartgold",
        "url": "https://pokeapi.co/api/v2/version/15/"
      }
    },
    {
      "flavor_text": "Ancient people believed that the\npattern on BRONZOR’s back\ncontained a mysterious power.",
      "language": {
        "name": "en",
        "url": "https://pokeapi.co/api/v2/language/9/"
      },
      "version": {
        "name": "soulsilver",
        "url": "https://pokeapi.co/api/v2/version/16/"
      }
    },
    {
      "flavor_text": "There are researchers who believe\nthis Pokémon reflected like a mirror\nin the distant past.",
      "language": {
        "name": "en",
        "url": "https://pokeapi.co/api/v2/language/9/"
      },
      "version": {
        "name": "black",
        "url": "https://pokeapi.co/api/v2/version/17/"
      }
    },
    {
      "flavor_text": "There are researchers who believe\nthis Pokémon reflected like a mirror\nin the distant past.",
      "language": {
        "name": "en",
        "url": "https://pokeapi.co/api/v2/language/9/"
      },
      "version": {
        "name": "white",
        "url": "https://pokeapi.co/api/v2/version/18/"
      }
    },
    {
      "flavor_text": "They are found in ancient tombs.\nThe patterns on their backs are\nsaid to be imbued with mysterious power.",
      "language": {
        "name": "en",
        "url": "https://pokeapi.co/api/v2/language/9/"
      },
      "version": {
        "name": "black-2",
        "url": "https://pokeapi.co/api/v2/version/21/"
      }
    },
    {
      "flavor_text": "They are found in ancient tombs.\nThe patterns on their backs are\nsaid to be imbued with mysterious power.",
      "language": {
        "name": "en",
        "url": "https://pokeapi.co/api/v2/language/9/"
      },
      "version": {
        "name": "white-2",
        "url": "https://pokeapi.co/api/v2/version/22/"
      }
    },
    {
      "flavor_text": "Ancient people believed that the pattern on\nBronzor’s back contained a mysterious power.",
      "language": {
        "name": "en",
        "url": "https://pokeapi.co/api/v2/language/9/"
      },
      "version": {
        "name": "x",
        "url": "https://pokeapi.co/api/v2/version/23/"
      }
    },
    {
      "flavor_text": "Implements shaped like it were discovered in\nancient tombs. It is unknown if they are related.",
      "language": {
        "name": "en",
        "url": "https://pokeapi.co/api/v2/language/9/"
      },
      "version": {
        "name": "y",
        "url": "https://pokeapi.co/api/v2/version/24/"
      }
    },
    {
      "flavor_text": "Ancient people believed that the pattern on\nBronzor’s back contained a mysterious power.",
      "language": {
        "name": "en",
        "url": "https://pokeapi.co/api/v2/language/9/"
      },
      "version": {
        "name": "omega-ruby",
        "url": "https://pokeapi.co/api/v2/version/25/"
      }
    },
    {
      "flavor_text": "Implements shaped like it were discovered in\nancient tombs. It is unknown if they are related.",
      "language": {
        "name": "en",
        "url": "https://pokeapi.co/api/v2/language/9/"
      },
      "version": {
        "name": "alpha-sapphire",
        "url": "https://pokeapi.co/api/v2/version/26/"
      }
    },
    {
      "flavor_text": "It appears in ancient ruins. The pattern on its\nbody doesn’t come from any culture in the\nGalar region, so it remains shrouded in mystery.",
      "language": {
        "name": "en",
        "url": "https://pokeapi.co/api/v2/language/9/"
      },
      "version": {
        "name": "sword",
        "url": "https://pokeapi.co/api/v2/version/33/"
      }
    },
    {
      "flavor_text": "Polishing Bronzor to a shine makes its surface\nreflect the truth, according to common lore.\nBe that as it may, Bronzor hates being polished.",
      "language": {
        "name": "en",
        "url": "https://pokeapi.co/api/v2/language/9/"
      },
      "version": {
        "name": "shield",
        "url": "https://pokeapi.co/api/v2/version/34/"
      }
    },
    {
      "flavor_text": "Floats using a mysterious energy. The pattern engraved upon its\nback is held as sacred and can sometimes be found in imagery\nfrom ancient cemeteries and other such timeworn places.",
      "language": {
        "name": "en",
        "url": "https://pokeapi.co/api/v2/language/9/"
      },
      "version": {
        "name": "legends-arceus",
        "url": "https://pokeapi.co/api/v2/version/39/"
      }
    }
  ]
}