{
  "id": 676,
  "name": "furfrou",
  "evolution_chain": {
    "url": "https://pokeapi.co/api/v2/evolution-chain/347/"
  },
  "flavor_text_entries": [
    {
      "flavor_text": "Trimming its fluffy fur not only makes\nit more elegant but also increases the\nswiftness of its movements.",
      "language": {
        "name": "en",
        "url": "https://pokeapi.co/api/v2/language/9/"
      },
      "version": {
        "name": "x",
        "url": "https://pokeapi.co/api/v2/version/23/"
      }
    },
    {
      "flavor_text": "Historically, in the Kalos region, these Pokémon\nwere the designated guardians of the king.",
      "language": {
        "name": "en",
        "url": "https://pokeapi.co/api/v2/language/9/"
      },
      "version": {
        "name": "y",
        "url": "https://pokeapi.co/api/v2/version/24/"
      }
    },
    {
      "flavor_text": "Trimming its fluffy fur not only makes\nit more elegant but also increases the\nswiftness of its movements.",
      "language": {
        "name": "en",
        "url": "https://pokeapi.co/api/v2/language/9/"
      },
      "version": {
        "name": "omega-ruby",
        "url": "https://pokeapi.co/api/v2/version/25/"
      }
    },
    {
      "flavor_text": "Historically, in the Kalos region, these Pokémon\nwere the designated guardians of the king.",
      "language": {
        "name": "en",
        "url": "https://pokeapi.co/api/v2/language/9/"
      },
      "version": {
        "name": "alpha-sapphire",
        "url": "https://pokeapi.co/api/v2/version/26/"
      }
    },
    {
      "flavor_text": "There was an era when aristocrats would\ncompete to see who could trim their Furfrou’s\nfur into the most exquisite style.",
      "language": {
        "name": "en",
        "url": "https://pokeapi.co/api/v2/language/9/"
      },
      "version": {
        "name": "ultra-sun",
        "url": "https://pokeapi.co/api/v2/version/29/"
      }
    },
    {
      "flavor_text": "Left alone, its fur will grow longer and longer,\nbut it will only allow someone it trusts to cut it.",
      "language": {
        "name": "en",
        "url": "https://pokeapi.co/api/v2/language/9/"
      },
      "version": {
        "name": "ultra-moon",
        "url": "https://pokeapi.co/api/v2/version/30/"
      }
    }
  ]
}