{
  "id": 679,
  "name": "honedge",
  "evolution_chain": {
    "url": "https://pokeapi.co/api/v2/evolution-chain/349/"
  },
  "flavor_text_entries": [
    {
      "flavor_text": "Apparently this Pokémon is born when a\ndeparted spirit inhabits a sword. It attaches itself\nto people and drinks their life force.",
      "language": {
        "name": "en",
        "url": "https://pokeapi.co/api/v2/language/9/"
      },
      "version": {
        "name": "x",
        "url": "https://pokeapi.co/api/v2/version/23/"
      }
    },
    {
      "flavor_text": "If anyone dares to grab its hilt, it wraps\na blue cloth around that person’s arm and\ndrains that person’s life energy completely.",
      "language": {
        "name": "en",
        "url": "https://pokeapi.co/api/v2/language/9/"
      },
      "version": {
        "name": "y",
        "url": "https://pokeapi.co/api/v2/version/24/"
      }
    },
    {
      "flavor_text": "Apparently this Pokémon is born when a\ndeparted spirit inhabits a sword. It attaches itself\nto people and drinks their life force.",
      "language": {
        "name": "en",
        "url": "https://pokeapi.co/api/v2/language/9/"
      },
      "version": {
        "name": "omega-ruby",
        "url": "https://pokeapi.co/api/v2/version/25/"
      }
    },
    {
      "flavor_text": "If anyone dares to grab its hilt, it wraps\na blue cloth around that person’s arm and\ndrains that person’s life energy completely.",
      "language": {
        "name": "en",
        "url": "https://pokeapi.co/api/v2/language/9/"
      },
      "version": {
        "name": "alpha-sapphire",
        "url": "https://pokeapi.co/api/v2/version/26/"
      }
    },
    {
      "flavor_text": "Honedge’s soul once belonged to a person who\nwas killed a long time ago by the sword that\nmakes up Honedge’s body.",
      "language": {
        "name": "en",
        "url": "https://pokeapi.co/api/v2/language/9/"
      },
      "version": {
        "name": "sword",
        "url": "https://pokeapi.co/api/v2/version/33/"
      }
    },
    {
      "flavor_text": "The blue eye on the sword’s handguard is the\ntrue body of Honedge. With its old cloth, it\ndrains people’s lives away.",
      "language": {
        "name": "en",
        "url": "https://pokeapi.co/api/v2/language/9/"
      },
      "version": {
        "name": "shield",
        "url": "https://pokeapi.co/api/v2/version/34/"
      }
    }
  ]
}