{
  "id": 784,
  "name": "kommo-o",
  "evolution_chain": {
    "url": "https://pokeapi.co/api/v2/evolution-chain/408/"
  },
  "flavor_text_entries": [
    {
      "flavor_text": "When it spots enemies, it threatens them by\njingling the scales on its tail. Weak opponents\nwill crack and flee in panic.",
      "language": {
        "name": "en",
        "url": "https://pokeapi.co/api/v2/language/9/"
      },
      "version": {
        "name": "sun",
        "url": "https://pokeapi.co/api/v2/version/27/"
      }
    },
    {
      "flavor_text": "Its rigid scales function as offense and defense.\nIn the past, its scales were processed and used\nto make weapons and other commodities.",
      "language": {
        "name": "en",
        "url": "https://pokeapi.co/api/v2/language/9/"
      },
      "version": {
        "name": "moon",
        "url": "https://pokeapi.co/api/v2/version/28/"
      }
    },
    {
      "flavor_text": "When it howls after finishing off its prey, the\nmetallic sounds of its celebrating comrades can\nbe heard from all around.",
      "language": {
        "name": "en",
        "url": "https://pokeapi.co/api/v2/language/9/"
      },
      "version": {
        "name": "ultra-sun",
        "url": "https://pokeapi.co/api/v2/version/29/"
      }
    },
    {
      "flavor_text": "It battles valiantly with its fists, which are\narmored in steel scales. Kommo-o specializes\nin uppercuts.",
      "language": {
        "name": "en",
        "url": "https://pokeapi.co/api/v2/language/9/"
      },
      "version": {
        "name": "ultra-moon",
        "url": "https://pokeapi.co/api/v2/version/30/"
      }
    },
    {
      "flavor_text": "It clatters its tail scales to unnerve opponents.\nThis Pokémon will battle only those who stand\nsteadfast in the face of this display.",
      "language": {
        "name": "en",
        "url": "https://pokeapi.co/api/v2/language/9/"
      },
      "version": {
        "name": "sword",
        "url": "https://pokeapi.co/api/v2/version/33/"
      }
    },
    {
      "flavor_text": "Certain ruins have paintings of ancient warriors\nwearing armor made of Kommo-o scales.",
      "language": {
        "name": "en",
        "url": "https://pokeapi.co/api/v2/language/9/"
      },
      "version": {
        "name": "shield",
        "url": "https://pokeapi.co/api/v2/version/34/"
      }
    }
  ]
}