{
  "id": 979,
  "name": "annihilape",
  "evolution_chain": {
    "url": "https://pokeapi.co/api/v2/evolution-chain/24/"
  },
  "flavor_text_entries": [
    {
      "flavor_text": "When its anger rose beyond a critical point, this Pokémon gained power that is unfettered by the limits of its physical body.",
      "language": {
        "name": "en",
        "url": "https://pokeapi.co/api/v2/language/9/"
      },
      "version": {
        "name": "scarlet",
        "url": "https://pokeapi.co/api/v2/version/40/"
      }
    },
    {
      "flavor_text": "It imbues its fists with the power of the rage that it kept hidden in its heart. Opponents struck by these imbued fists will be shattered to their core.",
      "language": {
        "name": "en",
        "url": "https://pokeapi.co/api/v2/language/9/"
      },
      "version": {
        "name": "violet",
        "url": "https://pokeapi.co/api/v2/version/41/"
      }
    }
  ]
}